GameWidgets/Constants.py
GameWidgets/__init__.py
GameWidgets/setup.py
GameWidgets/Editor/Editor.py
GameWidgets/Editor/__init__.py
GameWidgets/Engine/Backdrop.py
GameWidgets/Engine/Entity.py
GameWidgets/Engine/Group.py
GameWidgets/Engine/Manager.py
GameWidgets/Engine/Object.py
GameWidgets/Engine/ParticleEffect.py
GameWidgets/Engine/ScreenShade.py
GameWidgets/Engine/__init__.py
GameWidgets/Engine/PhysicsLib/__init__.py
GameWidgets/Engine/PhysicsLib/PhysicsConfig/World.py
GameWidgets/Engine/PhysicsLib/PhysicsConfig/__init__.py
GameWidgets/Engine/PhysicsLib/PhysicsObjects/PhysicsCircle.py
GameWidgets/Engine/PhysicsLib/PhysicsObjects/PhysicsObj.py
GameWidgets/Engine/PhysicsLib/PhysicsObjects/__init__.py
GameWidgets/Engine/Special/EnemyAI.py
GameWidgets/Engine/Special/Physics.py
GameWidgets/Engine/Special/TextEngine.py
GameWidgets/Engine/Special/TextEngineConsts.py
GameWidgets/Engine/Special/__init__.py
GameWidgets/GameWidgets/Animatrix.py
GameWidgets/GameWidgets/Draw.py
GameWidgets/GameWidgets/ScreenSlide.py
GameWidgets/GameWidgets/__init__.py
GameWidgets/GameWidgets/Controller/Button.py
GameWidgets/GameWidgets/Controller/Joystick.py
GameWidgets/GameWidgets/Controller/R1_R2.py
GameWidgets/GameWidgets/Controller/__init__.py
GameWidgets/GameWidgets/TileMaps/Sprite.py
GameWidgets/GameWidgets/TileMaps/Tile.py
GameWidgets/GameWidgets/TileMaps/__init__.py
GameWidgets/RuntimeTests/AllTest.py
GameWidgets/RuntimeTests/GameWidgetTest.py
GameWidgets/RuntimeTests/SetUpTest.py
GameWidgets/RuntimeTests/WidgetTest.py
GameWidgets/RuntimeTests/__init__.py
GameWidgets/SetUp/ScreenCommands.py
GameWidgets/SetUp/__init__.py
GameWidgets/Tools/GW_ANIMATOR.py
GameWidgets/Tools/GW_GAMEMAKER.py
GameWidgets/Tools/GW_PLIXEL.py
GameWidgets/Tools/Pixilate.py
GameWidgets/Tools/__init__.py
GameWidgets/Tools/Examples/ParticleEffectExample.py
GameWidgets/Tools/Examples/Widget_Screen_GameWidgets_Example.py
GameWidgets/Tools/Examples/__init__.py
GameWidgets/Widgets/Btn.py
GameWidgets/Widgets/Clock.py
GameWidgets-0.2.2.dist-info/METADATA
GameWidgets-0.2.2.dist-info/WHEEL
GameWidgets-0.2.2.dist-info/top_level.txt
GameWidgets-0.2.2.dist-info/RECORD
