Metadata-Version: 2.1
Name: GameWidgets
Version: 0.2.2
Summary: Make Game Easier with pygame and GameWidgets
Home-page: https://github.com/SuperGuy123456/GameWidgets
Author: Manomay tyagi
Author-email: tyagimanomay57@gmail.com
License: MIT
Requires-Python: >=3.8
Requires-Dist: pygame-ce
Requires-Dist: pillow
